ca_certificates/__init__.py
ofed_private_utils-0.0.0.dist-info/METADATA
ofed_private_utils-0.0.0.dist-info/WHEEL
ofed_private_utils-0.0.0.dist-info/top_level.txt
ofed_private_utils-0.0.0.dist-info/RECORD
