Metadata-Version: 2.4
Name: ofed-private-utils
Version: 0.0.0
Summary: Dummy ofed-private-utils package for PyPI
Author-email: Your Name <you@example.com>
Requires-Python: >=3.7
